moji/__init__.py
moji/dacc.py
moji/util.py
moji/data/emoji2vec.tsv
moji/data/emoji_joined.tsv
moji-0.0.8.dist-info/LICENSE
moji-0.0.8.dist-info/METADATA
moji-0.0.8.dist-info/WHEEL
moji-0.0.8.dist-info/top_level.txt
moji-0.0.8.dist-info/RECORD
