Metadata-Version: 2.1
Name: moji
Version: 0.0.8
Summary: Developing a full emoji language
Home-page: https://github.com/thorwhalen/moji
Author: Thor Whalen
License: apache-2.0
Platform: any
License-File: LICENSE
Requires-Dist: idiom
Requires-Dist: importlib-resources
Requires-Dist: numpy
